tm4c/__init__.py
tm4c/models/LeNet.py
tm4c/models/__init__.py
tm4c/models/config.py
tm4c/utils/__init__.py
tm4c/utils/common_utils.py
tm4c-0.0.0.dist-info/LICENSE
tm4c-0.0.0.dist-info/METADATA
tm4c-0.0.0.dist-info/WHEEL
tm4c-0.0.0.dist-info/top_level.txt
tm4c-0.0.0.dist-info/RECORD
